pycounts_geeto/__init__.py
pycounts_geeto/data/__init__.py
pycounts_geeto/data/flatland.txt
pycounts_geeto/datasets.py
pycounts_geeto/plotting.py
pycounts_geeto/pycounts_geeto.py
pycounts_geeto-0.3.0.dist-info/LICENSE
pycounts_geeto-0.3.0.dist-info/WHEEL
pycounts_geeto-0.3.0.dist-info/METADATA
pycounts_geeto-0.3.0.dist-info/RECORD
