Metadata-Version: 2.1
Name: pycounts-geeto
Version: 0.3.0
Summary: Calculate word counts in a text file!
License: MIT
Author: Kevin Robinson
Requires-Python: >=3.9,<4.0
Classifier: License :: OSI Approved :: MIT License
Classifier: Programming Language :: Python :: 3
Classifier: Programming Language :: Python :: 3.10
Classifier: Programming Language :: Python :: 3.9
Requires-Dist: matplotlib (>=3.5.2)
